_autosat_tseytin.cpython-37m-x86_64-linux-gnu.so
autosat-0.0.0.dist-info/LICENSE
autosat-0.0.0.dist-info/RECORD
autosat-0.0.0.dist-info/WHEEL
autosat-0.0.0.dist-info/METADATA
autosat-0.0.0.dist-info/top_level.txt
autosat/autosat_tseytin.py
autosat/__init__.py
